mcp_fooocus_api/__init__.py
mcp_fooocus_api/__main__.py
mcp_fooocus_api/server.py
mcp_fooocus_api-0.1.0.dist-info/METADATA
mcp_fooocus_api-0.1.0.dist-info/WHEEL
mcp_fooocus_api-0.1.0.dist-info/entry_points.txt
mcp_fooocus_api-0.1.0.dist-info/licenses/LICENSE
mcp_fooocus_api-0.1.0.dist-info/RECORD
