Metadata-Version: 2.4
Name: mcp-fooocus-api
Version: 0.1.0
Summary: MCP server for Fooocus Stable Diffusion API
Project-URL: Homepage, https://github.com/raihan0824/mcp-fooocus-api
Project-URL: Repository, https://github.com/raihan0824/mcp-fooocus-api
Project-URL: Issues, https://github.com/raihan0824/mcp-fooocus-api/issues
Project-URL: Documentation, https://github.com/raihan0824/mcp-fooocus-api#readme
Author-email: Raihan Afiandi <raihan.afiandi@lintasarta.co.id>
License: MIT
License-File: LICENSE
Keywords: ai,fooocus,image-generation,mcp,stable-diffusion
Classifier: Development Status :: 4 - Beta
Classifier: Intended Audience :: Developers
Classifier: License :: OSI Approved :: MIT License
Classifier: Programming Language :: Python :: 3
Classifier: Programming Language :: Python :: 3.10
Classifier: Programming Language :: Python :: 3.11
Classifier: Programming Language :: Python :: 3.12
Classifier: Programming Language :: Python :: 3.13
Classifier: Topic :: Internet :: WWW/HTTP :: HTTP Servers
Classifier: Topic :: Scientific/Engineering :: Artificial Intelligence
Classifier: Topic :: Software Development :: Libraries :: Python Modules
Requires-Python: >=3.10
Requires-Dist: anyio>=3.0.0
Requires-Dist: httpx>=0.27
Requires-Dist: jsonschema>=4.0.0
Requires-Dist: mcp>=1.0.0
Requires-Dist: pydantic<3.0.0,>=2.7.2
Requires-Dist: python-dotenv>=1.0.0
Provides-Extra: dev
Requires-Dist: black>=23.0.0; extra == 'dev'
Requires-Dist: mypy>=1.0.0; extra == 'dev'
Requires-Dist: pytest-asyncio>=0.21.0; extra == 'dev'
Requires-Dist: pytest>=7.0.0; extra == 'dev'
Requires-Dist: ruff>=0.1.0; extra == 'dev'
